.DS_Store
mugees/.DS_Store
mugees/__init__.py
mugees/depression.py
mugees-1.0.0.dist-info/LICENSE
mugees-1.0.0.dist-info/METADATA
mugees-1.0.0.dist-info/WHEEL
mugees-1.0.0.dist-info/top_level.txt
mugees-1.0.0.dist-info/RECORD
