Metadata-Version: 2.1
Name: mugees
Version: 1.0.0
Summary: A python library for detecting depressive comments
Author: Muhammad Mugees Asif
Classifier: Programming Language :: Python :: 3
Classifier: License :: OSI Approved :: Apache Software License
Classifier: Operating System :: OS Independent
Requires-Python: >=3.6
License-File: LICENSE
Requires-Dist: transformers (!=4.18.0)
Requires-Dist: torch (>=1.7.0)
Requires-Dist: sentencepiece (>=0.1.94)
